{"v":"4.10.1","fr":30,"ip":88,"op":114,"w":600,"h":125,"nm":"06-02-kr-medieval-out","ddd":0,"assets":[],"layers":[{"ddd":0,"ind":1,"ty":1,"nm":"Fractal","td":1,"sr":1,"ks":{"o":{"a":0,"k":100,"ix":11},"r":{"a":0,"k":0,"ix":10},"p":{"a":0,"k":[300,62.5,0],"ix":2},"a":{"a":0,"k":[300,62.5,0],"ix":1},"s":{"a":0,"k":[100,100,100],"ix":6}},"ao":0,"ef":[{"ty":5,"nm":"Fractal Noise","np":33,"mn":"ADBE Fractal Noise","ix":1,"en":1,"ef":[{"ty":7,"nm":"Fractal Type","mn":"ADBE Fractal Noise-0001","ix":1,"v":{"a":0,"k":7,"ix":1}},{"ty":7,"nm":"Noise Type","mn":"ADBE Fractal Noise-0002","ix":2,"v":{"a":0,"k":3,"ix":2}},{"ty":7,"nm":"Invert","mn":"ADBE Fractal Noise-0003","ix":3,"v":{"a":0,"k":1,"ix":3}},{"ty":0,"nm":"Contrast","mn":"ADBE Fractal Noise-0004","ix":4,"v":{"a":0,"k":100,"ix":4}},{"ty":0,"nm":"Brightness","mn":"ADBE Fractal Noise-0005","ix":5,"v":{"a":1,"k":[{"i":{"x":[0.833],"y":[0.833]},"o":{"x":[0.167],"y":[0.167]},"n":["0p833_0p833_0p167_0p167"],"t":0,"s":[-75],"e":[0]},{"i":{"x":[0.833],"y":[1]},"o":{"x":[0.333],"y":[0]},"n":["0p833_1_0p333_0"],"t":40,"s":[0],"e":[0]},{"i":{"x":[0.833],"y":[0.833]},"o":{"x":[0.167],"y":[0.167]},"n":["0p833_0p833_0p167_0p167"],"t":90,"s":[0],"e":[-75]},{"t":110}],"ix":5}},{"ty":7,"nm":"Overflow","mn":"ADBE Fractal Noise-0006","ix":6,"v":{"a":0,"k":4,"ix":6}},{"ty":6,"nm":"Transform","mn":"ADBE Fractal Noise-0007","ix":7,"v":0},{"ty":0,"nm":"Rotation","mn":"ADBE Fractal Noise-0008","ix":8,"v":{"a":0,"k":0,"ix":8}},{"ty":7,"nm":"Uniform Scaling","mn":"ADBE Fractal Noise-0009","ix":9,"v":{"a":0,"k":1,"ix":9}},{"ty":0,"nm":"Scale","mn":"ADBE Fractal Noise-0010","ix":10,"v":{"a":0,"k":100,"ix":10}},{"ty":0,"nm":"Scale Width","mn":"ADBE Fractal Noise-0011","ix":11,"v":{"a":0,"k":100,"ix":11}},{"ty":0,"nm":"Scale Height","mn":"ADBE Fractal Noise-0012","ix":12,"v":{"a":0,"k":100,"ix":12}},{"ty":3,"nm":"Offset Turbulence","mn":"ADBE Fractal Noise-0013","ix":13,"v":{"a":0,"k":[300,62.5],"ix":13}},{"ty":7,"nm":"Perspective Offset","mn":"ADBE Fractal Noise-0031","ix":14,"v":{"a":0,"k":0,"ix":14}},{"ty":6,"nm":"","mn":"ADBE Fractal Noise-0014","ix":15,"v":0},{"ty":0,"nm":"Complexity","mn":"ADBE Fractal Noise-0015","ix":16,"v":{"a":0,"k":6,"ix":16}},{"ty":6,"nm":"Sub Settings","mn":"ADBE Fractal Noise-0016","ix":17,"v":0},{"ty":0,"nm":"Sub Influence (%)","mn":"ADBE Fractal Noise-0017","ix":18,"v":{"a":0,"k":70,"ix":18}},{"ty":0,"nm":"Sub Scaling","mn":"ADBE Fractal Noise-0018","ix":19,"v":{"a":0,"k":56,"ix":19}},{"ty":0,"nm":"Sub Rotation","mn":"ADBE Fractal Noise-0019","ix":20,"v":{"a":0,"k":0,"ix":20}},{"ty":3,"nm":"Sub Offset","mn":"ADBE Fractal Noise-0020","ix":21,"v":{"a":0,"k":[0,0],"ix":21}},{"ty":7,"nm":"Center Subscale","mn":"ADBE Fractal Noise-0021","ix":22,"v":{"a":0,"k":0,"ix":22}},{"ty":6,"nm":"","mn":"ADBE Fractal Noise-0022","ix":23,"v":0},{"ty":0,"nm":"Evolution","mn":"ADBE Fractal Noise-0023","ix":24,"v":{"a":0,"k":35,"ix":24}},{"ty":6,"nm":"Evolution Options","mn":"ADBE Fractal Noise-0024","ix":25,"v":0},{"ty":7,"nm":"Cycle Evolution","mn":"ADBE Fractal Noise-0025","ix":26,"v":{"a":0,"k":0,"ix":26}},{"ty":0,"nm":"Cycle (in Revolutions)","mn":"ADBE Fractal Noise-0026","ix":27,"v":{"a":0,"k":1,"ix":27}},{"ty":0,"nm":"Random Seed","mn":"ADBE Fractal Noise-0027","ix":28,"v":{"a":0,"k":0,"ix":28}},{"ty":6,"nm":"Random Seed","mn":"ADBE Fractal Noise-0028","ix":29,"v":0},{"ty":0,"nm":"Opacity","mn":"ADBE Fractal Noise-0029","ix":30,"v":{"a":0,"k":100,"ix":30}},{"ty":7,"nm":"Blending Mode","mn":"ADBE Fractal Noise-0030","ix":31,"v":{"a":0,"k":2,"ix":31}}]},{"ty":5,"nm":"Exposure","np":24,"mn":"ADBE Exposure2","ix":2,"en":1,"ef":[{"ty":7,"nm":"Channels:","mn":"ADBE Exposure2-0001","ix":1,"v":{"a":0,"k":1,"ix":1}},{"ty":6,"nm":"Master","mn":"ADBE Exposure2-0002","ix":2,"v":0},{"ty":0,"nm":"Exposure","mn":"ADBE Exposure2-0003","ix":3,"v":{"a":0,"k":15,"ix":3}},{"ty":0,"nm":"Offset","mn":"ADBE Exposure2-0004","ix":4,"v":{"a":0,"k":0,"ix":4}},{"ty":0,"nm":"Gamma Correction","mn":"ADBE Exposure2-0005","ix":5,"v":{"a":0,"k":1,"ix":5}},{"ty":6,"nm":"Master","mn":"ADBE Exposure2-0006","ix":6,"v":0},{"ty":6,"nm":"Red","mn":"ADBE Exposure2-0007","ix":7,"v":0},{"ty":0,"nm":"Red Exposure","mn":"ADBE Exposure2-0008","ix":8,"v":{"a":0,"k":0,"ix":8}},{"ty":0,"nm":"Red Offset","mn":"ADBE Exposure2-0009","ix":9,"v":{"a":0,"k":0,"ix":9}},{"ty":0,"nm":"Red Gamma Correction","mn":"ADBE Exposure2-0010","ix":10,"v":{"a":0,"k":1,"ix":10}},{"ty":6,"nm":"Red","mn":"ADBE Exposure2-0011","ix":11,"v":0},{"ty":6,"nm":"Green","mn":"ADBE Exposure2-0012","ix":12,"v":0},{"ty":0,"nm":"Green Exposure","mn":"ADBE Exposure2-0013","ix":13,"v":{"a":0,"k":0,"ix":13}},{"ty":0,"nm":"Green Offset","mn":"ADBE Exposure2-0014","ix":14,"v":{"a":0,"k":0,"ix":14}},{"ty":0,"nm":"Green Gamma Correction","mn":"ADBE Exposure2-0015","ix":15,"v":{"a":0,"k":1,"ix":15}},{"ty":6,"nm":"Green","mn":"ADBE Exposure2-0016","ix":16,"v":0},{"ty":6,"nm":"Blue","mn":"ADBE Exposure2-0017","ix":17,"v":0},{"ty":0,"nm":"Blue Exposure","mn":"ADBE Exposure2-0018","ix":18,"v":{"a":0,"k":0,"ix":18}},{"ty":0,"nm":"Blue Offset","mn":"ADBE Exposure2-0019","ix":19,"v":{"a":0,"k":0,"ix":19}},{"ty":0,"nm":"Blue Gamma Correction","mn":"ADBE Exposure2-0020","ix":20,"v":{"a":0,"k":1,"ix":20}},{"ty":6,"nm":"Blue","mn":"ADBE Exposure2-0021","ix":21,"v":0},{"ty":7,"nm":"Bypass Linear Light Conversion","mn":"ADBE Exposure2-0022","ix":22,"v":{"a":0,"k":0,"ix":22}}]},{"ty":5,"nm":"CC Vector Blur","np":9,"mn":"CC Vector Blur","ix":3,"en":1,"ef":[{"ty":7,"nm":"Type","mn":"CC Vector Blur-0001","ix":1,"v":{"a":0,"k":3,"ix":1}},{"ty":0,"nm":"Amount","mn":"CC Vector Blur-0002","ix":2,"v":{"a":0,"k":2,"ix":2}},{"ty":0,"nm":"Angle Offset","mn":"CC Vector Blur-0003","ix":3,"v":{"a":0,"k":0,"ix":3}},{"ty":0,"nm":"Ridge Smoothness","mn":"CC Vector Blur-0004","ix":4,"v":{"a":0,"k":1,"ix":4}},{"ty":10,"nm":"Vector Map","mn":"CC Vector Blur-0005","ix":5,"v":{"a":0,"k":0,"ix":5}},{"ty":7,"nm":"Property","mn":"CC Vector Blur-0006","ix":6,"v":{"a":0,"k":5,"ix":6}},{"ty":0,"nm":"Map Softness","mn":"CC Vector Blur-0007","ix":7,"v":{"a":0,"k":15,"ix":7}}]}],"sw":600,"sh":125,"sc":"#000000","ip":0,"op":150,"st":0,"bm":0},{"ddd":0,"ind":2,"ty":1,"nm":"Deep Turquoise Solid 2","tt":3,"sr":1,"ks":{"o":{"a":0,"k":100,"ix":11},"r":{"a":0,"k":0,"ix":10},"p":{"a":0,"k":[300,62.5,0],"ix":2},"a":{"a":0,"k":[300,62.5,0],"ix":1},"s":{"a":0,"k":[100,100,100],"ix":6}},"ao":0,"hasMask":true,"masksProperties":[{"inv":false,"mode":"f","pt":{"a":0,"k":{"i":[[0.525,0],[0,0],[0,-0.525],[0,0],[-0.525,0],[0,0],[0,0.525],[0,0]],"o":[[0,0],[-0.525,0],[0,0],[0,0.525],[0,0],[0.525,0],[0,0],[0,-0.525]],"v":[[216.996,46.847],[158.965,46.847],[158.014,47.797],[158.014,54.774],[158.965,55.724],[216.996,55.724],[217.946,54.774],[217.946,47.797]],"c":true},"ix":1},"o":{"a":0,"k":100,"ix":3},"x":{"a":0,"k":0,"ix":4},"nm":"Mask 1"},{"inv":false,"mode":"f","pt":{"a":0,"k":{"i":[[0.525,0],[0,0],[0,-0.525],[0,0],[-0.525,0],[0,0],[0,0.525],[0,0]],"o":[[0,0],[-0.525,0],[0,0],[0,0.525],[0,0],[0.525,0],[0,0],[0,-0.525]],"v":[[275.69,27.188],[268.714,27.188],[267.764,28.139],[267.764,80.433],[268.714,81.383],[275.69,81.383],[276.641,80.433],[276.641,28.139]],"c":true},"ix":1},"o":{"a":0,"k":100,"ix":3},"x":{"a":0,"k":0,"ix":4},"nm":"Mask 2"},{"inv":false,"mode":"f","pt":{"a":0,"k":{"i":[[0.525,0],[0,0],[0,-0.525],[0,0],[-0.525,0],[0,0],[0,0],[0,0],[0,0],[-0.525,0],[0,0],[0,0.525],[0,0],[0.525,0],[0,0],[0,0],[0,0],[0,0.525],[0,0]],"o":[[0,0],[-0.525,0],[0,0],[0,0.525],[0,0],[0,0],[0,0],[0,0],[0,0.525],[0,0],[0.525,0],[0,0],[0,-0.525],[0,0],[0,0],[0,0],[0.525,0],[0,0],[0,-0.525]],"v":[[404.449,30.053],[368.781,30.053],[367.831,31.004],[367.831,37.98],[368.781,38.931],[373.389,38.931],[373.389,69.359],[373.389,72.904],[373.389,76.335],[374.339,77.286],[404.449,77.286],[405.4,76.335],[405.4,69.359],[404.449,68.408],[382.266,68.408],[382.266,38.931],[404.449,38.931],[405.4,37.98],[405.4,31.004]],"c":true},"ix":1},"o":{"a":0,"k":100,"ix":3},"x":{"a":0,"k":0,"ix":4},"nm":"Mask 3"},{"inv":false,"mode":"f","pt":{"a":0,"k":{"i":[[0.525,0],[0,0],[0,-0.525],[0,0],[-0.525,0],[0,0],[0,0.525],[0,0]],"o":[[0,0],[-0.525,0],[0,0],[0,0.525],[0,0],[0.525,0],[0,0],[0,-0.525]],"v":[[289.349,24.841],[282.373,24.841],[281.423,25.791],[281.423,81.089],[282.373,82.04],[289.349,82.04],[290.3,81.089],[290.3,25.791]],"c":true},"ix":1},"o":{"a":0,"k":100,"ix":3},"x":{"a":0,"k":0,"ix":4},"nm":"Mask 4"},{"inv":false,"mode":"f","pt":{"a":0,"k":{"i":[[0.525,0],[0,0],[0,-0.525],[0,0],[-0.525,0],[0,0],[0,0.525],[0,0]],"o":[[0,0],[-0.525,0],[0,0],[0,0.525],[0,0],[0.525,0],[0,0],[0,-0.525]],"v":[[355.128,24.841],[348.152,24.841],[347.202,25.791],[347.202,80.774],[348.152,81.724],[355.128,81.724],[356.079,80.774],[356.079,25.791]],"c":true},"ix":1},"o":{"a":0,"k":100,"ix":3},"x":{"a":0,"k":0,"ix":4},"nm":"Mask 5"},{"inv":false,"mode":"f","pt":{"a":0,"k":{"i":[[0.525,0],[0,0],[0,-0.525],[0,0],[-0.525,0],[0,0],[0,0.525],[0,0]],"o":[[0,0],[-0.525,0],[0,0],[0,0.525],[0,0],[0.525,0],[0,0],[0,-0.525]],"v":[[415.966,25.997],[408.99,25.997],[408.039,26.947],[408.039,79.618],[408.99,80.568],[415.966,80.568],[416.916,79.618],[416.916,26.947]],"c":true},"ix":1},"o":{"a":0,"k":100,"ix":3},"x":{"a":0,"k":0,"ix":4},"nm":"Mask 6"},{"inv":false,"mode":"f","pt":{"a":0,"k":{"i":[[0.525,0],[0,0],[0,-0.525],[0,0],[-0.525,0],[0,0],[0,0.525],[0,0]],"o":[[0,0],[-0.525,0],[0,0],[0,0.525],[0,0],[0.525,0],[0,0],[0,-0.525]],"v":[[441.035,25.997],[434.059,25.997],[433.108,26.947],[433.108,79.618],[434.059,80.568],[441.035,80.568],[441.985,79.618],[441.985,26.947]],"c":true},"ix":1},"o":{"a":0,"k":100,"ix":3},"x":{"a":0,"k":0,"ix":4},"nm":"Mask 7"},{"inv":false,"mode":"f","pt":{"a":0,"k":{"i":[[0,0],[-0.371,0.371],[0,0],[-0.371,-0.371],[0,0],[-0.371,0.371],[0,0],[0.371,0.371],[0,0],[0,0],[0,0.525],[0,0],[0.525,0],[0,0],[0,-0.525],[0,0],[-0.525,0],[0,0],[0,0],[-0.371,-0.371]],"o":[[0.371,0.371],[0,0],[0.371,-0.371],[0,0],[0.371,0.371],[0,0],[0.371,-0.371],[0,0],[0,0],[0.525,0],[0,0],[0,-0.525],[0,0],[-0.525,0],[0,0],[0,0.525],[0,0],[0,0],[-0.371,0.371],[0,0]],"v":[[160.77,45.173],[162.114,45.173],[187.308,36.979],[188.652,36.979],[213.846,45.173],[215.19,45.173],[217.123,40.24],[217.123,38.896],[198.975,32.653],[214.668,32.653],[215.618,31.703],[215.618,24.727],[214.668,23.776],[161.293,23.776],[160.342,24.727],[160.342,31.703],[161.293,32.653],[176.985,32.653],[158.837,38.896],[158.837,40.24]],"c":true},"ix":1},"o":{"a":0,"k":100,"ix":3},"x":{"a":0,"k":0,"ix":4},"nm":"Mask 8"},{"inv":false,"mode":"f","pt":{"a":0,"k":{"i":[[0,0],[0.379,-0.531],[0,0],[-0.427,-0.305],[0,0],[-0.305,0.427],[0,0],[0,0],[-0.427,0.305],[0,0],[0.305,0.427]],"o":[[-0.379,-0.531],[0,0],[-0.305,0.427],[0,0],[0.427,0.305],[0,0],[0,0],[0.305,0.427],[0,0],[0.427,-0.305],[0,0]],"v":[[239.997,26.123],[238.449,26.123],[221.885,67.753],[222.107,69.079],[227.786,73.13],[229.112,72.909],[239.275,44.672],[250.334,72.909],[251.66,73.13],[257.339,69.079],[257.561,67.753]],"c":true},"ix":1},"o":{"a":0,"k":100,"ix":3},"x":{"a":0,"k":0,"ix":4},"nm":"Mask 9"},{"inv":false,"mode":"f","pt":{"a":0,"k":{"i":[[0,0],[0,0],[0.354,-0.685],[0,0],[0,0],[-0.466,-0.241],[0,0],[-0.241,0.466],[0,0],[0,0],[-0.466,0.241],[0,0],[0.241,0.466]],"o":[[0,0],[-0.354,-0.685],[0,0],[0,0],[-0.241,0.466],[0,0],[0.466,0.241],[0,0],[0,0],[0.241,0.466],[0,0],[0.466,-0.241],[0,0]],"v":[[323.702,39.176],[319.548,31.148],[317.86,31.148],[313.707,39.176],[295.68,74.016],[296.087,75.297],[302.283,78.502],[303.564,78.095],[318.704,48.834],[333.844,78.095],[335.125,78.502],[341.321,75.297],[341.729,74.016]],"c":true},"ix":1},"o":{"a":0,"k":100,"ix":3},"x":{"a":0,"k":0,"ix":4},"nm":"Mask 10"},{"inv":false,"mode":"f","pt":{"a":0,"k":{"i":[[0,3.328],[3.328,0],[0,-3.328],[-3.328,0]],"o":[[0,-3.328],[-3.328,0],[0,3.328],[3.328,0]],"v":[[194.006,62.671],[187.98,56.646],[181.955,62.671],[187.98,68.696]],"c":true},"ix":1},"o":{"a":0,"k":100,"ix":3},"x":{"a":0,"k":0,"ix":4},"nm":"Mask 11"},{"inv":false,"mode":"f","pt":{"a":0,"k":{"i":[[3.328,0],[0,-3.328],[-3.328,0],[0,3.328]],"o":[[-3.328,0],[0,3.328],[3.328,0],[0,-3.328]],"v":[[424.942,47.257],[418.917,53.282],[424.942,59.308],[430.967,53.282]],"c":true},"ix":1},"o":{"a":0,"k":100,"ix":3},"x":{"a":0,"k":0,"ix":4},"nm":"Mask 12"},{"inv":false,"mode":"f","pt":{"a":0,"k":{"i":[[3.328,0],[0,-3.328],[-3.328,0],[0,3.328]],"o":[[-3.328,0],[0,3.328],[3.328,0],[0,-3.328]],"v":[[259.942,47.257],[253.917,53.282],[259.942,59.308],[265.967,53.282]],"c":true},"ix":1},"o":{"a":0,"k":100,"ix":3},"x":{"a":0,"k":0,"ix":4},"nm":"Mask 13"},{"inv":false,"mode":"f","pt":{"a":0,"k":{"i":[[8.547,0],[0,-8.547],[-8.547,0],[0,8.547]],"o":[[-8.547,0],[0,8.547],[8.547,0],[0,-8.547]],"v":[[188.093,70.224],[172.593,85.724],[188.093,101.224],[203.593,85.724]],"c":true},"ix":1},"o":{"a":0,"k":100,"ix":3},"x":{"a":0,"k":0,"ix":4},"nm":"Mask 14"},{"inv":false,"mode":"f","pt":{"a":0,"k":{"i":[[3.584,0],[0,3.584],[-3.584,0],[0,-3.584]],"o":[[-3.584,0],[0,-3.584],[3.584,0],[0,3.584]],"v":[[188.093,92.224],[181.593,85.724],[188.093,79.224],[194.593,85.724]],"c":true},"ix":1},"o":{"a":0,"k":100,"ix":3},"x":{"a":0,"k":0,"ix":4},"nm":"Mask 15"}],"sw":600,"sh":125,"sc":"#0a6024","ip":0,"op":150,"st":0,"bm":1}]}